woe/GridSearch.py
woe/__init__.py
woe/config.py
woe/eval.py
woe/feature_process.py
woe/ftrl.py
woe-0.1.4.dist-info/DESCRIPTION.rst
woe-0.1.4.dist-info/METADATA
woe-0.1.4.dist-info/RECORD
woe-0.1.4.dist-info/WHEEL
woe-0.1.4.dist-info/metadata.json
woe-0.1.4.dist-info/top_level.txt
