Metadata-Version: 2.0
Name: woe
Version: 0.1.4
Summary: Tools for WoE Transformation mostly used in ScoreCard Model for credit rating
Home-page: https://github.com/boredbird/woe
Author: boredbird
Author-email: 1002937942@qq.com
License: MIT
Keywords: math,finance,scorecard,woe,iv
Platform: all
Classifier: Operating System :: OS Independent
Classifier: Intended Audience :: Developers
Classifier: License :: OSI Approved :: MIT License
Classifier: Programming Language :: Python
Classifier: Programming Language :: Python :: Implementation
Classifier: Programming Language :: Python :: 2
Classifier: Programming Language :: Python :: 2.7
Classifier: Programming Language :: Python :: 3
Classifier: Programming Language :: Python :: 3.5
Classifier: Topic :: Software Development :: Libraries
Requires-Dist: matplotlib (>=2.0.0)
Requires-Dist: numpy (>=1.11.3)
Requires-Dist: pandas (>=0.19.2)
Requires-Dist: scipy (>=0.18.1)
